{
  "languages": [
    {
      "code": "TR",
      "name": "Türkçe",
      "items": [
        {"key": "categoryTitle", "value": "Bir Kategori Seçin"},
        {"key": "question", "value": "Soru"},
        {"key": "categorySubtitle", "value": "Dini Kim Milyoner Olmak İster?"},
        {"key": "fiftyFifty", "value": "Yarı Yarıya"},
        {"key": "askAudience", "value": "Seyirci"},
        {"key": "phoneFriend", "value": "Telefon"},
        {"key": "walkAway", "value": "Çekil"},
        {"key": "ok", "value": "Tamam"},
        {"key": "mainMenu", "value": "Ana Menü"},
        {"key": "settings", "value": "Ayarlar"},
        {"key": "close", "value": "Kapat"},
        {"key": "musicVolume", "value": "Müzik Ses Seviyesi"},
        {"key": "sfxVolume", "value": "Efekt Ses Seviyesi"},
        {"key": "muteAll", "value": "Tümünü Sessize Al"},
        {"key": "start", "value": "Başla"},
        {"key": "congratulations", "value": "🎉 Tebrikler!"},
        {"key": "winMessage", "value": "Tüm 15 soruyu doğru cevapladınız!\n\n{0} kazandınız!"},
        {"key": "wrongAnswer", "value": "Yanlış Cevap!"},
        {"key": "correctAnswerWas", "value": "Doğru cevap şuydu:"},
        {"key": "youDropTo", "value": "Şu seviyeye düştünüz:"},
        {"key": "timesUp", "value": "Süre Doldu!"},
        {"key": "timesUpMsg", "value": "Soruyu cevaplamak için süreniz doldu."},
        {"key": "wisdomOfDay", "value": "💡 Günün Öğüdü"},
        {"key": "continue", "value": "Devam Et"}
      ]
    },
    {
      "code": "EN",
      "name": "English",
      "items": [
        {"key": "categoryTitle", "value": "Choose a Category"},
        {"key": "question", "value": "Question"},
        {"key": "categorySubtitle", "value": "Religious Who Wants to Be a Millionaire?"},
        {"key": "fiftyFifty", "value": "50:50"},
        {"key": "askAudience", "value": "Ask Aud"},
        {"key": "phoneFriend", "value": "Phone"},
        {"key": "walkAway", "value": "Walk Away"},
        {"key": "ok", "value": "OK"},
        {"key": "mainMenu", "value": "Main Menu"},
        {"key": "settings", "value": "Settings"},
        {"key": "close", "value": "Close"},
        {"key": "musicVolume", "value": "Music Volume"},
        {"key": "sfxVolume", "value": "SFX Volume"},
        {"key": "muteAll", "value": "Mute All"},
        {"key": "start", "value": "Start"},
        {"key": "congratulations", "value": "🎉 Congratulations!"},
        {"key": "winMessage", "value": "You answered all 15 questions correctly!\n\nYou won {0}!"},
        {"key": "wrongAnswer", "value": "Wrong Answer!"},
        {"key": "correctAnswerWas", "value": "The correct answer was:"},
        {"key": "youDropTo", "value": "You drop to the guaranteed level:"},
        {"key": "timesUp", "value": "Time's Up!"},
        {"key": "timesUpMsg", "value": "You ran out of time to answer the question."},
        {"key": "wisdomOfDay", "value": "💡 Wisdom of the Day"},
        {"key": "continue", "value": "Continue"}
      ]
    },
    {
      "code": "AR",
      "name": "العربية",
      "items": [
        {"key": "categoryTitle", "value": "اختر فئة"},
        {"key": "question", "value": "سؤال"},
        {"key": "categorySubtitle", "value": "من سيربح المليونير الديني؟"},
        {"key": "fiftyFifty", "value": "50:50"},
        {"key": "askAudience", "value": "اسأل الجمهور"},
        {"key": "phoneFriend", "value": "اتصل بصديق"},
        {"key": "walkAway", "value": "انسحاب"},
        {"key": "ok", "value": "تم"},
        {"key": "mainMenu", "value": "القائمة الرئيسية"},
        {"key": "settings", "value": "الإعدادات"},
        {"key": "close", "value": "إغلاق"},
        {"key": "musicVolume", "value": "مستوى صوت الموسيقى"},
        {"key": "sfxVolume", "value": "مستوى صوت المؤثرات"},
        {"key": "muteAll", "value": "كتم الكل"},
        {"key": "start", "value": "ابدأ"},
        {"key": "congratulations", "value": "🎉 تهانينا!"},
        {"key": "winMessage", "value": "لقد أجبت على جميع الأسئلة الـ 15 بشكل صحيح!\n\nلقد ربحت {0}!"},
        {"key": "wrongAnswer", "value": "إجابة خاطئة!"},
        {"key": "correctAnswerWas", "value": "كانت الإجابة الصحيحة هي:"},
        {"key": "youDropTo", "value": "لقد هبطت إلى المستوى المضمون:"},
        {"key": "timesUp", "value": "انتهى الوقت!"},
        {"key": "timesUpMsg", "value": "لقد نفد وقتك للإجابة على السؤال."},
        {"key": "wisdomOfDay", "value": "💡 حكمة اليوم"},
        {"key": "continue", "value": "استمر"}
      ]
    },
    {
      "code": "DE",
      "name": "Deutsch",
      "items": [
        {"key": "categoryTitle", "value": "Wähle eine Kategorie"},
        {"key": "question", "value": "Frage"},
        {"key": "categorySubtitle", "value": "Religiöses Wer wird Millionär?"},
        {"key": "fiftyFifty", "value": "50:50"},
        {"key": "askAudience", "value": "Publikum"},
        {"key": "phoneFriend", "value": "Telefon"},
        {"key": "walkAway", "value": "Aussteigen"},
        {"key": "ok", "value": "OK"},
        {"key": "mainMenu", "value": "Hauptmenü"},
        {"key": "settings", "value": "Einstellungen"},
        {"key": "close", "value": "Schließen"},
        {"key": "musicVolume", "value": "Musiklautstärke"},
        {"key": "sfxVolume", "value": "Effektlautstärke"},
        {"key": "muteAll", "value": "Alle stummschalten"},
        {"key": "start", "value": "Start"},
        {"key": "congratulations", "value": "🎉 Herzlichen Glückwunsch!"},
        {"key": "winMessage", "value": "Du hast alle 15 Fragen richtig beantwortet!\n\nDu hast {0} gewonnen!"},
        {"key": "wrongAnswer", "value": "Falsche Antwort!"},
        {"key": "correctAnswerWas", "value": "Die richtige Antwort war:"},
        {"key": "youDropTo", "value": "Du fällst auf das garantierte Niveau:"},
        {"key": "timesUp", "value": "Zeit abgelaufen!"},
        {"key": "timesUpMsg", "value": "Die Zeit zur Beantwortung der Frage ist abgelaufen."},
        {"key": "wisdomOfDay", "value": "💡 Weisheit des Tages"},
        {"key": "continue", "value": "Weiter"}
      ]
    },
    {
      "code": "FR",
      "name": "Français",
      "items": [
        {"key": "categoryTitle", "value": "Choisissez une catégorie"},
        {"key": "question", "value": "Question"},
        {"key": "categorySubtitle", "value": "Qui veut gagner des millions religieux ?"},
        {"key": "fiftyFifty", "value": "50:50"},
        {"key": "askAudience", "value": "Public"},
        {"key": "phoneFriend", "value": "Téléphone"},
        {"key": "walkAway", "value": "Partir"},
        {"key": "ok", "value": "OK"},
        {"key": "mainMenu", "value": "Menu principal"},
        {"key": "settings", "value": "Paramètres"},
        {"key": "close", "value": "Fermer"},
        {"key": "musicVolume", "value": "Volume musique"},
        {"key": "sfxVolume", "value": "Volume effets"},
        {"key": "muteAll", "value": "Tout couper"},
        {"key": "start", "value": "Commencer"},
        {"key": "congratulations", "value": "🎉 Félicitations !"},
        {"key": "winMessage", "value": "Vous avez répondu correctement aux 15 questions !\n\nVous avez gagné {0} !"},
        {"key": "wrongAnswer", "value": "Mauvaise réponse !"},
        {"key": "correctAnswerWas", "value": "La bonne réponse était :"},
        {"key": "youDropTo", "value": "Vous tombez au niveau garanti :"},
        {"key": "timesUp", "value": "Temps écoulé !"},
        {"key": "timesUpMsg", "value": "Vous n'avez plus de temps pour répondre à la question."},
        {"key": "wisdomOfDay", "value": "💡 Sagesse du jour"},
        {"key": "continue", "value": "Continuer"}
      ]
    },
    {
      "code": "ID",
      "name": "Bahasa Indonesia",
      "items": [
        {"key": "categoryTitle", "value": "Pilih Kategori"},
        {"key": "question", "value": "Pertanyaan"},
        {"key": "categorySubtitle", "value": "Siapa Ingin Menjadi Jutawan Religi?"},
        {"key": "fiftyFifty", "value": "50:50"},
        {"key": "askAudience", "value": "Tanya Penonton"},
        {"key": "phoneFriend", "value": "Telepon Teman"},
        {"key": "walkAway", "value": "Berhenti"},
        {"key": "ok", "value": "OK"},
        {"key": "mainMenu", "value": "Menu Utama"},
        {"key": "settings", "value": "Pengaturan"},
        {"key": "close", "value": "Tutup"},
        {"key": "musicVolume", "value": "Volume Musik"},
        {"key": "sfxVolume", "value": "Volume SFX"},
        {"key": "muteAll", "value": "Bisukan Semua"},
        {"key": "start", "value": "Mulai"},
        {"key": "congratulations", "value": "🎉 Selamat!"},
        {"key": "winMessage", "value": "Anda menjawab semua 15 pertanyaan dengan benar!\n\nAnda memenangkan {0}!"},
        {"key": "wrongAnswer", "value": "Jawaban Salah!"},
        {"key": "correctAnswerWas", "value": "Jawaban yang benar adalah:"},
        {"key": "youDropTo", "value": "Anda turun ke level yang dijamin:"},
        {"key": "timesUp", "value": "Waktu Habis!"},
        {"key": "timesUpMsg", "value": "Waktu Anda untuk menjawab pertanyaan telah habis."},
        {"key": "wisdomOfDay", "value": "💡 Kebijaksanaan Hari Ini"},
        {"key": "continue", "value": "Lanjutkan"}
      ]
    },
    {
      "code": "UR",
      "name": "اردو",
      "items": [
        {"key": "categoryTitle", "value": "زمرہ منتخب کریں"},
        {"key": "question", "value": "سوال"},
        {"key": "categorySubtitle", "value": "مذہبی کون بنے گا کروڑ پتی؟"},
        {"key": "fiftyFifty", "value": "50:50"},
        {"key": "askAudience", "value": "سامعین سے پوچھیں"},
        {"key": "phoneFriend", "value": "دوست کو فون کریں"},
        {"key": "walkAway", "value": "چھوڑ دیں"},
        {"key": "ok", "value": "ٹھیک ہے"},
        {"key": "mainMenu", "value": "مین مینو"},
        {"key": "settings", "value": "ترتیبات"},
        {"key": "close", "value": "بند کریں"},
        {"key": "musicVolume", "value": "میوزک والیوم"},
        {"key": "sfxVolume", "value": "ایس ایف ایکس والیوم"},
        {"key": "muteAll", "value": "سب خاموش کریں"},
        {"key": "start", "value": "شروع کریں"},
        {"key": "congratulations", "value": "🎉 مبارک ہو!"},
        {"key": "winMessage", "value": "آپ نے تمام 15 سوالات کے صحیح جوابات دیئے!\n\nآپ نے {0} جیت لیے!"},
        {"key": "wrongAnswer", "value": "غلط جواب!"},
        {"key": "correctAnswerWas", "value": "صحیح جواب یہ تھا:"},
        {"key": "youDropTo", "value": "آپ ضمانت شدہ سطح پر آگئے ہیں:"},
        {"key": "timesUp", "value": "وقت ختم!"},
        {"key": "timesUpMsg", "value": "سوال کا جواب دینے کے لیے آپ کا وقت ختم ہو گیا ہے۔"},
        {"key": "wisdomOfDay", "value": "💡 آج کی حکمت"},
        {"key": "continue", "value": "جاری رکھیں"}
      ]
    }
  ]
}
